virtru_sdk.cpython-310-darwin.so
virtru_sdk-3.0.0.dist-info/METADATA
virtru_sdk-3.0.0.dist-info/WHEEL
virtru_sdk-3.0.0.dist-info/top_level.txt
virtru_sdk-3.0.0.dist-info/RECORD
